Metadata-Version: 2.1
Name: weeb-fast-hist
Version: 3.1.0
Summary: A example Python package for itmo da course
Home-page: UNKNOWN
Author: Garanin Artem
Author-email: 
License: UNKNOWN
Platform: UNKNOWN
